[
	{"dano":{"Один":"0", "Два":"0", "Три":"0", "Система":"Windows"},"itog":{"Два":"0", "Количество":"0", "Значение":"Обширное"}},
	{"dano":{"Один":"0", "Два":"0", "Три":"1", "Система":"Linux"},"itog":{"Два":"0", "Количество":"1", "Значение":"Обширное"}},
	{"dano":{"Один":"0", "Два":"1", "Три":"0", "Система":"Windows"},"itog":{"Два":"0", "Количество":"1", "Значение":"Другое"}},
	{"dano":{"Один":"0", "Два":"1", "Три":"1", "Система":"Windows"},"itog":{"Два":"1", "Количество":"1", "Значение":"Обширное"}},
	{"dano":{"Один":"1", "Два":"0", "Три":"0", "Система":"Windows"},"itog":{"Два":"0", "Количество":"1", "Значение":"Обширное"}},
	{"dano":{"Один":"1", "Два":"0", "Три":"1", "Система":"Windows"},"itog":{"Два":"1", "Количество":"1", "Значение":"Обширное"}},
	{"dano":{"Один":"1", "Два":"1", "Три":"0", "Система":"Windows"},"itog":{"Два":"1", "Количество":"1", "Значение":"Обширное"}},
	{"dano":{"Один":"1", "Два":"1", "Три":"1", "Система":"Windows"},"itog":{"Два":"0", "Количество":"1", "Значение":"Обширное"}}
]
